textmining/__init__.py
textmining/cli.py
textmining/stemmer.py
textmining/data/dictionary.txt
textmining/data/names_female.txt
textmining/data/names_last.txt
textmining/data/names_male.txt
textmining/data/stopwords.txt
textmining/doc/poscodes.html
textmining/examples/examples.py
textmining/examples/holmes.txt
textmining3-1.1.0.dist-info/AUTHORS.rst
textmining3-1.1.0.dist-info/LICENSE
textmining3-1.1.0.dist-info/METADATA
textmining3-1.1.0.dist-info/WHEEL
textmining3-1.1.0.dist-info/entry_points.txt
textmining3-1.1.0.dist-info/top_level.txt
textmining3-1.1.0.dist-info/RECORD
