Metadata-Version: 2.1
Name: textmining3
Version: 1.1.0
Summary: Text Mining Utilities for Python 3
Home-page: https://github.com/djcomlab/textmining3
Author: David Johnson
Author-email: djcomlab@gmail.com
License: GNU General Public License v3
Keywords: textmining3
Platform: UNKNOWN
Classifier: Development Status :: 5 - Production/Stable
Classifier: Intended Audience :: Developers
Classifier: Intended Audience :: Science/Research
Classifier: License :: OSI Approved :: GNU General Public License v3 (GPLv3)
Classifier: Natural Language :: English
Classifier: Operating System :: OS Independent
Classifier: Programming Language :: Python :: 3
Classifier: Programming Language :: Python :: 3.6
Classifier: Programming Language :: Python :: 3.7
Classifier: Topic :: Scientific/Engineering :: Artificial Intelligence
Classifier: Topic :: Scientific/Engineering :: Information Analysis
Classifier: Topic :: Text Processing :: General
Classifier: Topic :: Text Processing :: Linguistic
Requires-Dist: Click (>=6.0)
Provides-Extra: pandas
Requires-Dist: pandas (>=0.23.4); extra == 'pandas'
